odoo9_addon_l10n_br_base-9.0.1.0.0.99.dev3-py2.7-nspkg.pth
odoo9_addon_l10n_br_base-9.0.1.0.0.99.dev3.dist-info/METADATA
odoo9_addon_l10n_br_base-9.0.1.0.0.99.dev3.dist-info/RECORD
odoo9_addon_l10n_br_base-9.0.1.0.0.99.dev3.dist-info/WHEEL
odoo9_addon_l10n_br_base-9.0.1.0.0.99.dev3.dist-info/namespace_packages.txt
odoo9_addon_l10n_br_base-9.0.1.0.0.99.dev3.dist-info/top_level.txt
odoo_addons/l10n_br_base/README.rst
odoo_addons/l10n_br_base/__init__.py
odoo_addons/l10n_br_base/__openerp__.py
odoo_addons/l10n_br_base/data/l10n_br_base.city.csv
odoo_addons/l10n_br_base/data/l10n_br_base_data.xml
odoo_addons/l10n_br_base/data/res.country.state.csv
odoo_addons/l10n_br_base/demo/l10n_br_base_demo.xml
odoo_addons/l10n_br_base/demo/res_partner_demo.xml
odoo_addons/l10n_br_base/i18n/pt_BR.po
odoo_addons/l10n_br_base/migrations/8.0.1.0.1/openupgrade_analysis.txt
odoo_addons/l10n_br_base/migrations/8.0.1.0.1/openupgrade_analysis_work.txt
odoo_addons/l10n_br_base/models/__init__.py
odoo_addons/l10n_br_base/models/l10n_br_base.py
odoo_addons/l10n_br_base/models/res_bank.py
odoo_addons/l10n_br_base/models/res_company.py
odoo_addons/l10n_br_base/models/res_config.py
odoo_addons/l10n_br_base/models/res_country.py
odoo_addons/l10n_br_base/models/res_partner.py
odoo_addons/l10n_br_base/security/ir.model.access.csv
odoo_addons/l10n_br_base/static/description/icon.png
odoo_addons/l10n_br_base/test/base_inscr_est_invalid.yml
odoo_addons/l10n_br_base/test/base_inscr_est_valid.yml
odoo_addons/l10n_br_base/test/res_company_test.yml
odoo_addons/l10n_br_base/test/res_partner_test.yml
odoo_addons/l10n_br_base/tests/__init__.py
odoo_addons/l10n_br_base/tests/test_amount_to_text.py
odoo_addons/l10n_br_base/tools/__init__.py
odoo_addons/l10n_br_base/tools/fiscal.py
odoo_addons/l10n_br_base/tools/misc.py
odoo_addons/l10n_br_base/views/l10n_br_base_view.xml
odoo_addons/l10n_br_base/views/res_bank_view.xml
odoo_addons/l10n_br_base/views/res_company_view.xml
odoo_addons/l10n_br_base/views/res_country_view.xml
odoo_addons/l10n_br_base/views/res_partner_view.xml
