Metadata-Version: 2.1
Name: odoo9-addon-l10n-br-base
Version: 9.0.1.0.0.99.dev3
Summary: Brazilian Localization Base
Home-page: http://odoo-brasil.org
Author: Akretion, Odoo Community Association (OCA)
Author-email: support@odoo-community.org
License: AGPL-3
Platform: UNKNOWN
Classifier: Programming Language :: Python
Classifier: Framework :: Odoo
Classifier: License :: OSI Approved :: GNU Affero General Public License v3
Requires-Python: ~=2.7
Requires-Dist: num2words
Requires-Dist: odoo (<9.1a,>=9.0a)
